anime_quotes/__init__.py
anime_quotes/__main__.py
anime_quotes/quotes.json
anime_quotes/quotes.py
anime_quotes-0.1.8.dist-info/licenses/LICENSE
anime_quotes-0.1.8.dist-info/METADATA
anime_quotes-0.1.8.dist-info/WHEEL
anime_quotes-0.1.8.dist-info/entry_points.txt
anime_quotes-0.1.8.dist-info/top_level.txt
anime_quotes-0.1.8.dist-info/RECORD
