Metadata-Version: 2.4
Name: anime-quotes
Version: 0.1.8
Summary: Random anime quotes generator to motivate your burn-out soul
Author-email: Aldi Hermansyah <alher6555@gmail.com>
License: MIT
Keywords: quotes,anime,motivation,fun
Classifier: Programming Language :: Python :: 3
Classifier: License :: OSI Approved :: MIT License
Classifier: Operating System :: OS Independent
Requires-Python: >=3.7
License-File: LICENSE
Dynamic: license-file
